packages/__init__.py
topsispkg-0.0.3.dist-info/LICENSE.txt
topsispkg-0.0.3.dist-info/METADATA
topsispkg-0.0.3.dist-info/WHEEL
topsispkg-0.0.3.dist-info/top_level.txt
topsispkg-0.0.3.dist-info/RECORD
