Metadata-Version: 2.1
Name: topsispkg
Version: 0.0.3
Summary: UCS633/psrana:This package will rank your input on the basis of topsis
Home-page: UNKNOWN
Author: Priyanshu Gupta
Author-email: priyanshugupta1904@gmail.com.com
License: UNKNOWN
Platform: UNKNOWN
Classifier: Programming Language :: Python :: 3
Classifier: License :: OSI Approved :: MIT License
Classifier: Operating System :: OS Independent
Requires-Python: >=3.6
